git_when_merged.py
git_when_merged-6.6.6.dist-info/COPYING
git_when_merged-6.6.6.dist-info/METADATA
git_when_merged-6.6.6.dist-info/WHEEL
git_when_merged-6.6.6.dist-info/entry_points.txt
git_when_merged-6.6.6.dist-info/top_level.txt
git_when_merged-6.6.6.dist-info/RECORD
