Metadata-Version: 2.1
Name: git-when-merged
Version: 6.6.6
Summary: Determine when a particular commit was merged into a git branch
Home-page: https://pypi.org/project/git-when-merged
Author: Michael Haggerty
Author-email: mhagger@alum.mit.edu
License: GPLv2+
Project-URL: Code, https://github.com/mhagger/git-when-merged
Project-URL: Issues, https://github.com/mhagger/git-when-merged/issues
Classifier: License :: OSI Approved :: GNU General Public License v2 or later (GPLv2+)
Classifier: Development Status :: 5 - Production/Stable
Classifier: Intended Audience :: Developers
Classifier: Intended Audience :: End Users/Desktop
Classifier: Topic :: Software Development :: Version Control
Classifier: Topic :: Software Development :: Version Control :: Git
Classifier: Topic :: Utilities
Classifier: Environment :: Console
Requires-Python: >= 3.7
License-File: COPYING
